{
  "schemaVersion": 1,
  "id": "moe-utils",
  "version": "${version}",
  "name": "MoeUtils",
  "description": "Mapart utilities, featuring slimmed down edition of V's printer.",
  "authors": [
    "loli-tummy",
    "Kyuunex"
  ],
  "contact": {
    "email": "kyuunex@protonmail.ch",
    "repo": "https://github.com/Kyuunex/moe-utils"
  },
  "icon": "assets/moe-utils/icon.png",
  "environment": "client",
  "entrypoints": {
    "meteor": [
      "moe.kyuunex.moe_utils.MoeUtils"
    ]
  },
  "mixins": [
    "litematica_moe-utils.mixins.json"
  ],
  "custom": {
    "meteor-client:color": "225,25,25"
  },
  "depends": {
    "java": ">=21",
    "minecraft": "${mc_version}",
    "meteor-client": "*"
  }
}
